Workbook

Sheet Read Me
A1: ARGUMENTAL · INVESTOR MODEL · 3-YEAR
A2: How this model works
A4: This workbook is the working financial model behind the Argumental seed deck.
A5: All five tabs are linked: change a cell on Assumptions and every downstream
A6: number updates.
A8: Tabs
A9: 1. Read Me — this page.
A10: 2. Assumptions — every input the model uses, in one place. Cells with a
A11: pale-blue fill are inputs you can edit; everything else is a formula.
A12: 3. Bouts & Audience — month-by-month viewer ramp and bouts per year.
A13: 4. P&L (3-Year) — revenue, variable costs, gross margin, fixed opex,
A14: EBITDA. Year-over-year columns plus a running 3-year total.
... A54: · Tax — model is pre-tax EBITDA only.

Sheet Assumptions
A1: INPUTS — EDIT THESE TO STRESS-TEST
A2: Assumptions
A4: Driver | B4: 2026 (Y1) | C4: 2027 (Y2) | D4: 2028 (Y3) | E4: Notes
A6: AUDIENCE & ENGAGEMENT
A7: Bouts per year | B7: 48 | C7: 48 | D7: 48 | E7: 1 / Sunday
A8: Avg concurrent live viewers / bout | B8: 30000 | C8: 100000 | D8: 250000 | E8: Y1 ramp targets 100K EOY
A9: % of viewers who vote | B9: 0.06 | C9: 0.08 | D9: 0.09 | E9: Single $5 vote
A10: Avg vote price (USD) | B10: 5 | C10: 5 | D10: 5 | E10: Fixed
A12: SPONSORSHIP
A13: Sponsor revenue / bout (USD) | B13: 0 | C13: 30000 | D13: 75000 | E13: Title slot · 41× reach
A14: Sponsored bouts (% of cadence) | B14: 0 | C14: 0.5 | D14: 1 | E14: Brand fit
A16: VARIABLE COSTS · PER BOUT
A17: Mux delivery $/viewer-hour | B17: 0.06 | C17: 0.06 | D17: 0.05 | E17: Negotiated at scale
A18: Mux ingest $/bout (2 streams) | B18: 8 | C18: 8 | D18: 8 | E18: 24m × 2 streams
A19: Stripe rate (% of vote rev) | B19: 0.029 | C19: 0.029 | D19: 0.029 | E19: + $0.30/vote
A20: Stripe per-vote fee | B20: 0.3 | C20: 0.3 | D20: 0.3 | E20: Flat
A21: Charity payout (% of vote rev) | B21: 0.18 | C21: 0.18 | D21: 0.18 | E21: 18% donor model
A22: Debater honorarium / bout | B22: 25000 | C22: 25000 | D22: 25000 | E22: Capped at $25K (both)
A23: Production / bout | B23: 12000 | C23: 18000 | D23: 25000 | E23: Studio + crew
A25: FIXED COSTS · PER YEAR
A26: Headcount (FTE) | B26: 4 | C26: 8 | D26: 14 | E26: Avg loaded $180K
A27: Loaded cost per FTE | B27: 180000 | C27: 180000 | D27: 195000 | E27: Salary + benefits
A28: Paid search & acquisition | B28: 120000 | C28: 240000 | D28: 360000 | E28: $10K/mo Y1
A29: Brand & creator marketing | B29: 60000 | C29: 240000 | D29: 480000 | E29: Sponsored clips
A30: G&A, tooling, infra | B30: 60000 | C30: 120000 | D30: 200000 | E30: Office, software
A31: Legal, accounting, insurance | B31: 50000 | C31: 90000 | D31: 140000 | E31: Outside counsel
A33: AUDIENCE BEHAVIOR
A34: Avg minutes watched / live viewer | B34: 16 | C34: 18 | D34: 20 | E34: Drives live Mux delivery cost
A35: Post-live replay multiplier | B35: 40 | C35: 40 | D35: 40 | E35: Replay views = live × this. Bout 24h+ archive.
A36: Avg minutes watched / replay viewer | B36: 4 | C36: 5 | D36: 6 | E36: Highlights & clips, not full bout

Sheet Bouts & Audience
A1: VOLUME
A2: Bouts and viewers, by year
A4: Metric | B4: 2026 | C4: 2027 | D4: 2028 | E4: 3-Yr Total
A6: Bouts per year | B6: =Assumptions!B7 | C6: =Assumptions!C7 | D6: =Assumptions!D7 | E6: =SUM(B6:D6)
A7: Avg concurrent viewers / bout | B7: =Assumptions!B8 | C7: =Assumptions!C8 | D7: =Assumptions!D8
A8: Annual viewer-bouts | B8: =B6*B7 | C8: =C6*C7 | D8: =D6*D7 | E8: =SUM(B8:D8)
A9: Voter conversion rate | B9: =Assumptions!B9 | C9: =Assumptions!C9 | D9: =Assumptions!D9
A10: Votes per bout | B10: =B7*B9 | C10: =C7*C9 | D10: =D7*D9
A11: Annual votes | B11: =B6*B10 | C11: =C6*C10 | D11: =D6*D10 | E11: =SUM(B11:D11)
A13: Avg minutes watched / live viewer | B13: =Assumptions!B34 | C13: =Assumptions!C34 | D13: =Assumptions!D34
A14: Annual viewer-hours delivered (Mux) | B14: =B8*(B13+Assumptions!B35*Assumptions!B36)/60 | C14: =C8*(C13+Assumptions!C35*Assumptions!C36)/60 | D14: =D8*(D13+Assumptions!D35*Assumptions!D36)/60 | E14: =SUM(B14:D14)
A16: REACH BEYOND LIVE
A17: Post-live replay multiplier | B17: =Assumptions!B35 | C17: =Assumptions!C35 | D17: =Assumptions!D35
A18: Replay viewers / bout | B18: =B7*B17 | C18: =C7*C17 | D18: =D7*D17
A19: Total reach / bout (live + replay) | B19: =B7+B18 | C19: =C7+C18 | D19: =D7+D18
A20: Annual total impressions | B20: =B6*B19 | C20: =C6*C19 | D20: =D6*D19 | E20: =SUM(B20:D20)

Sheet P&L (3-Year)
A1: REVENUE · VARIABLE COSTS · GROSS MARGIN · OPEX · EBITDA
A2: P&L — 3-Year View
B4: 2026 | C4: 2027 | D4: 2028 | E4: 3-Yr Total
A6: REVENUE
A7: Voting revenue | B7: ='Bouts & Audience'!B11*Assumptions!B10 | C7: ='Bouts & Audience'!C11*Assumptions!C10 | D7: ='Bouts & Audience'!D11*Assumptions!D10 | E7: =SUM(B7:D7)
A8: Sponsor revenue | B8: =Assumptions!B7*Assumptions!B14*Assumptions!B13 | C8: =Assumptions!C7*Assumptions!C14*Assumptions!C13 | D8: =Assumptions!D7*Assumptions!D14*Assumptions!D13 | E8: =SUM(B8:D8)
A9: Total revenue | B9: =SUM(B7:B8) | C9: =SUM(C7:C8) | D9: =SUM(D7:D8) | E9: =SUM(B9:D9)
A11: VARIABLE COSTS · COGS
A12: Mux delivery (CDN) | B12: ='Bouts & Audience'!B14*Assumptions!B17 | C12: ='Bouts & Audience'!C14*Assumptions!C17 | D12: ='Bouts & Audience'!D14*Assumptions!D17
A13: Mux ingest | B13: =Assumptions!B7*Assumptions!B18 | C13: =Assumptions!C7*Assumptions!C18 | D13: =Assumptions!D7*Assumptions!D18
A14: Stripe processing | B14: =B7*Assumptions!B19+'Bouts & Audience'!B11*Assumptions!B20 | C14: =C7*Assumptions!C19+'Bouts & Audience'!C11*Assumptions!C20 | D14: =D7*Assumptions!D19+'Bouts & Audience'!D11*Assumptions!D20
A15: Charity payout (18% of vote rev) | B15: =B7*Assumptions!B21 | C15: =C7*Assumptions!C21 | D15: =D7*Assumptions!D21
A16: Debater honorariums | B16: =Assumptions!B7*Assumptions!B22 | C16: =Assumptions!C7*Assumptions!C22 | D16: =Assumptions!D7*Assumptions!D22
A17: Production | B17: =Assumptions!B7*Assumptions!B23 | C17: =Assumptions!C7*Assumptions!C23 | D17: =Assumptions!D7*Assumptions!D23
A18: Total variable cost | B18: =SUM(B12:B17) | C18: =SUM(C12:C17) | D18: =SUM(D12:D17) | E18: =SUM(B18:D18)
A20: GROSS MARGIN
A21: Gross profit | B21: =B9-B18 | C21: =C9-C18 | D21: =D9-D18 | E21: =SUM(B21:D21)
A22: Gross margin % | B22: =IFERROR(B21/B9,0) | C22: =IFERROR(C21/C9,0) | D22: =IFERROR(D21/D9,0)
A24: FIXED OPEX
A25: Headcount cost | B25: =Assumptions!B26*Assumptions!B27 | C25: =Assumptions!C26*Assumptions!C27 | D25: =Assumptions!D26*Assumptions!D27
A26: Paid search & acquisition | B26: =Assumptions!B28 | C26: =Assumptions!C28 | D26: =Assumptions!D28
A27: Brand & creator marketing | B27: =Assumptions!B29 | C27: =Assumptions!C29 | D27: =Assumptions!D29
A28: G&A, tooling, infra | B28: =Assumptions!B30 | C28: =Assumptions!C30 | D28: =Assumptions!D30
A29: Legal, accounting, insurance | B29: =Assumptions!B31 | C29: =Assumptions!C31 | D29: =Assumptions!D31
A30: Total fixed opex | B30: =SUM(B25:B29) | C30: =SUM(C25:C29) | D30: =SUM(D25:D29) | E30: =SUM(B30:D30)
A32: EBITDA
A33: EBITDA | B33: =B21-B30 | C33: =C21-C30 | D33: =D21-D30 | E33: =SUM(B33:D33)
A34: EBITDA margin % | B34: =IFERROR(B33/B9,0) | C34: =IFERROR(C33/C9,0) | D34: =IFERROR(D33/D9,0)
A37: Pre-tax. Excludes IP/licensing upside.

Sheet Unit Economics
A1: PER-BOUT CONTRIBUTION MARGIN AT THREE AUDIENCE SCALES
A2: Unit Economics — per bout
B4: Year 1 scale | C4: Year 2 scale | D4: Year 3 scale
A6: Avg viewers / bout | B6: =Assumptions!B8 | C6: =Assumptions!C8 | D6: =Assumptions!D8
A7: Voters / bout | B7: =B6*Assumptions!B9 | C7: =C6*Assumptions!C9 | D7: =D6*Assumptions!D9
A9: REVENUE / BOUT
A10: Voting | B10: =B7*Assumptions!B10 | C10: =C7*Assumptions!C10 | D10: =D7*Assumptions!D10
A11: Sponsor share | B11: =Assumptions!B13*Assumptions!B14 | C11: =Assumptions!C13*Assumptions!C14 | D11: =Assumptions!D13*Assumptions!D14
A12: Total revenue / bout | B12: =SUM(B10:B11) | C12: =SUM(C10:C11) | D12: =SUM(D10:D11)
A14: VARIABLE COST / BOUT
A15: Mux delivery (live + replay) | B15: =B6*(Assumptions!B34+Assumptions!B35*Assumptions!B36)/60*Assumptions!B17 | C15: =C6*(Assumptions!C34+Assumptions!C35*Assumptions!C36)/60*Assumptions!C17 | D15: =D6*(Assumptions!D34+Assumptions!D35*Assumptions!D36)/60*Assumptions!D17
A16: Mux ingest | B16: =Assumptions!B18 | C16: =Assumptions!C18 | D16: =Assumptions!D18
A17: Stripe processing | B17: =B10*Assumptions!B19+B7*Assumptions!B20 | C17: =C10*Assumptions!C19+C7*Assumptions!C20 | D17: =D10*Assumptions!D19+D7*Assumptions!D20
A18: Charity payout | B18: =B10*Assumptions!B21 | C18: =C10*Assumptions!C21 | D18: =D10*Assumptions!D21
A19: Debater honorariums | B19: =Assumptions!B22 | C19: =Assumptions!C22 | D19: =Assumptions!D22
A20: Production | B20: =Assumptions!B23 | C20: =Assumptions!C23 | D20: =Assumptions!D23
A21: Total variable cost / bout | B21: =SUM(B15:B20) | C21: =SUM(C15:C20) | D21: =SUM(D15:D20)
A23: CONTRIBUTION MARGIN / BOUT
A24: Contribution $ | B24: =B12-B21 | C24: =C12-C21 | D24: =D12-D21
A25: Contribution % | B25: =IFERROR(B24/B12,0) | C25: =IFERROR(C24/C12,0) | D25: =IFERROR(D24/D12,0)
A27: Excludes fixed opex. See P&L tab for full picture.
